routrie-0.8.0.dist-info/METADATA
routrie-0.8.0.dist-info/WHEEL
routrie-0.8.0.dist-info/license_files/LICENSE.txt
routrie.libs/libgcc_s-133c3184.so.1
routrie/py.typed
routrie/__init__.py
routrie/_routrie.pyi
routrie/_routrie.abi3.so
routrie-0.8.0.dist-info/RECORD
