Metadata-Version: 2.1
Name: routrie
Version: 0.8.0
Classifier: Development Status :: 3 - Alpha
Classifier: Intended Audience :: Developers
Classifier: License :: OSI Approved :: MIT License
Classifier: Topic :: Software Development
Classifier: Topic :: Software Development :: Libraries
Classifier: Topic :: Software Development :: Libraries :: Python Modules
License-File: LICENSE.txt
Summary: Python wrapper for https://github.com/viz-rs/path-tree
Author: Adrian Garcia Badaracco
License: MIT
Requires-Python: >=3.7
Project-URL: documentation, https://github.com/adriangb/routrie/README.md
Project-URL: repository, https://github.com/adriangb/routrie
Project-URL: homepage, https://github.com/adriangb/routrie
